yente/__init__.py
yente/app.py
yente/asgi.py
yente/cli.py
yente/exc.py
yente/logs.py
yente/py.typed
yente/scoring.py
yente/server.py
yente/settings.py
yente/util.py
yente/data/__init__.py
yente/data/common.py
yente/data/dataset.py
yente/data/entity.py
yente/data/freebase.py
yente/data/loader.py
yente/data/manifest.py
yente/data/updater.py
yente/data/util.py
yente/middleware/__init__.py
yente/middleware/request_log.py
yente/middleware/trace_context.py
yente/provider/__init__.py
yente/provider/base.py
yente/provider/elastic.py
yente/provider/opensearch.py
yente/resources/favicon.ico
yente/routers/__init__.py
yente/routers/admin.py
yente/routers/match.py
yente/routers/reconcile.py
yente/routers/search.py
yente/routers/util.py
yente/search/__init__.py
yente/search/audit_log.py
yente/search/indexer.py
yente/search/lock.py
yente/search/mapping.py
yente/search/nested.py
yente/search/queries.py
yente/search/search.py
yente/search/status.py
yente/search/versions.py
yente-5.0.1.dist-info/METADATA
yente-5.0.1.dist-info/WHEEL
yente-5.0.1.dist-info/entry_points.txt
yente-5.0.1.dist-info/licenses/LICENSE
yente-5.0.1.dist-info/RECORD
