Metadata-Version: 2.4
Name: yente
Version: 5.0.1
Summary: A simple and fast API service for querying FollowTheMoney data, including OpenSanctions.
Project-URL: Documentation, https://www.opensanctions.org/docs/yente/
Project-URL: Repository, https://github.com/opensanctions/yente.git
Project-URL: Issues, https://github.com/opensanctions/yente/issues
Author-email: OpenSanctions <info@opensanctions.org>
License: MIT License
License-File: LICENSE
Requires-Python: <=3.13,>=3.11
Requires-Dist: aiocron==2.1
Requires-Dist: aiocsv==1.3.2
Requires-Dist: aiofiles==24.1.0
Requires-Dist: aiohttp[speedups]==3.12.15
Requires-Dist: anyio==4.10.0
Requires-Dist: asyncstdlib==3.13.1
Requires-Dist: boto3~=1.37
Requires-Dist: click~=8.2.0
Requires-Dist: countrynames==1.16.10
Requires-Dist: cryptography==46.0.1
Requires-Dist: elasticsearch[async]==8.19.1
Requires-Dist: email-validator==2.3.0
Requires-Dist: fastapi==0.116.2
Requires-Dist: fingerprints==1.3.1
Requires-Dist: followthemoney>=4.2.2
Requires-Dist: httpx[http2]==0.28.1
Requires-Dist: jellyfish==1.2.0
Requires-Dist: nomenklatura==4.1.8
Requires-Dist: normality==3.0.2
Requires-Dist: opensearch-py[async]==3.0.0
Requires-Dist: orjson==3.11.3
Requires-Dist: pydantic
Requires-Dist: pyicu==2.15.3
Requires-Dist: python-multipart==0.0.20
Requires-Dist: rich
Requires-Dist: rigour==1.3.7
Requires-Dist: structlog==25.4.0
Requires-Dist: text-unidecode==1.3
Requires-Dist: uvicorn[standard]==0.35.0
Provides-Extra: dev
Requires-Dist: black<26.0,>=24.10; extra == 'dev'
Requires-Dist: boto3-stubs~=1.37; extra == 'dev'
Requires-Dist: build; extra == 'dev'
Requires-Dist: bump2version==1.0.1; extra == 'dev'
Requires-Dist: flake8>=2.6.0; extra == 'dev'
Requires-Dist: mypy~=1.13; extra == 'dev'
Requires-Dist: pip>10.0.0; extra == 'dev'
Requires-Dist: pre-commit; extra == 'dev'
Requires-Dist: pytest-asyncio<2.0.0,>=0.25.0; extra == 'dev'
Requires-Dist: pytest-cov<8.0.0,>=6.0.0; extra == 'dev'
Requires-Dist: pytest-httpx<1.0.0,==0.35.0; extra == 'dev'
Requires-Dist: pytest==8.4.2; extra == 'dev'
Requires-Dist: ruff<1.0.0,>=0.8.4; extra == 'dev'
Requires-Dist: types-aiofiles<25.0,>=24.0; extra == 'dev'
Requires-Dist: types-pyyaml; extra == 'dev'
Provides-Extra: docs
Requires-Dist: cairosvg; extra == 'docs'
Requires-Dist: mkdocs; extra == 'docs'
Requires-Dist: mkdocs-macros-plugin; extra == 'docs'
Requires-Dist: mkdocs-material; extra == 'docs'
Requires-Dist: mkdocstrings[python]; extra == 'docs'
Requires-Dist: pillow; extra == 'docs'
